tablefile/__init__.py
tablefile/file.py
tablefile-0.0.5.dist-info/METADATA
tablefile-0.0.5.dist-info/WHEEL
tablefile-0.0.5.dist-info/license.txt
tablefile-0.0.5.dist-info/top_level.txt
tablefile-0.0.5.dist-info/RECORD
