Metadata-Version: 2.1
Name: tablefile
Version: 0.0.5
Summary: A package for reading and processing tabular data files for analytical applications
Home-page: https://github.com/dwaipayandeb/scifile
Author: Dwaipayan Deb
Author-email: dwaipayandeb@yahoo.co.in
License: UNKNOWN
Platform: UNKNOWN
Classifier: Programming Language :: Python :: 3
Classifier: License :: OSI Approved :: MIT License
Classifier: Operating System :: OS Independent
Requires-Python: >=3.6
License-File: license.txt
